merge_requirements
