Metadata-Version: 1.1
Name: merge-requirements
Version: 0.6
Summary: simple lib for organize two requirements.txt in a unique requirements.txt file
Home-page: https://github.com/victorhos/merge_requirements
Author: victorhos
Author-email: victor.hos@gmail.com
License: MIT
Keywords: merge requirements
Platform: UNKNOWN
Classifier: Development Status :: 5 - Production/Stable
Classifier: License :: OSI Approved :: MIT License
Classifier: Programming Language :: Python :: 3.4
Classifier: Programming Language :: Python :: 2.7
